_nlwpy.cpython-37m-aarch64-linux-gnu.so
nlwpy-0.0.1b0.dist-info/LICENSE
nlwpy-0.0.1b0.dist-info/WHEEL
nlwpy-0.0.1b0.dist-info/METADATA
nlwpy-0.0.1b0.dist-info/top_level.txt
nlwpy-0.0.1b0.dist-info/RECORD
nlwpy/__init__.py
nlwpy/docs/conf.py
nlwpy/test/test_solve.py
nlwpy/test/__init__.py
nlwpy/test/__main__.py
