Metadata-Version: 2.1
Name: nlwpy
Version: 0.0.1b0
Summary: Python API for the AMPL NL Writer library
Home-page: https://github.com/ampl/mp
Author: Gleb Belov
Author-email: gleb@ampl.com
License: BSD-3
Requires-Python: >=3.7
License-File: LICENSE
Provides-Extra: test
Requires-Dist: pytest ; extra == 'test'
